lsiwh_simulate/__init__.py
lsiwh_simulate/customer.py
lsiwh_simulate/sim.py
lsiwh_simulate-0.1.10.dist-info/METADATA
lsiwh_simulate-0.1.10.dist-info/WHEEL
lsiwh_simulate-0.1.10.dist-info/entry_points.txt
lsiwh_simulate-0.1.10.dist-info/top_level.txt
lsiwh_simulate-0.1.10.dist-info/RECORD
