Metadata-Version: 2.1
Name: lsiwh_simulate
Version: 0.1.10
Summary: Default template for PDM package
Author-email: lsiwh37249 <lsiwh37249@gmail.com>
License: MIT
Requires-Python: ==3.11.*
Requires-Dist: simpy>=4.1.1
